setup.cfg
setup.py
tensors/__init__.py
tensors.egg-info/PKG-INFO
tensors.egg-info/SOURCES.txt
tensors.egg-info/dependency_links.txt
tensors.egg-info/not-zip-safe
tensors.egg-info/requires.txt
tensors.egg-info/top_level.txt
tensors/backends/__init__.py
tensors/backends/none/__init__.py
tensors/backends/qtt/__init__.py
tensors/backends/qtt/helpers.py
tensors/backends/qtt/matrix.py
tensors/backends/qtt/vector.py
tensors/frontend/__init__.py
tensors/frontend/matrix.py
tensors/frontend/scalar.py
tensors/frontend/settings.py
tensors/frontend/tensor.py
tensors/frontend/tools.py
tensors/frontend/vector.py