Metadata-Version: 1.1
Name: tensors
Version: 0.1
Summary: Interface for working with low-rank tensor approximations
Home-page: https://bitbucket.org/thoughteer/tensors
Author: Iskander Sitdikov
Author-email: thoughteer@gmail.com
License: MIT
Keywords: tensor low-rank TT vector matrix
Platform: UNKNOWN
Classifier: Development Status :: 4 - Beta
Classifier: License :: OSI Approved :: MIT License
Classifier: Programming Language :: Python :: 3.4
Classifier: Topic :: Scientific/Engineering :: Mathematics
